Workbook

Sheet Executive Summary
A1: BLOOM — At-Home Salon & Beauty Services Platform
A2: Module-Wise Requirements — Executive Summary (Phase 1: Salon & Beauty Home Services)
A3: Prepared for IT Delivery Team | Draft v1.0 | September 2026
A5: Module ID | B5: Module Name | C5: Category | D5: Primary Persona(s) | E5: Platform(s) | F5: Priority | G5: # of Requirements | H5: Module Description
A6: M01 | B6: Customer Onboarding & Profile Management | C6: Customer-Facing | D6: End Customer | E6: Customer Android App, Customer iOS App, Website | F6: P0 | G6: =COUNTIF('Detailed Requirements'!$A$6:$A$5000,A6) -> 6 | H6: Registration, login and profile management for end customers.
A7: M02 | B7: Address & Location Management | C7: Customer-Facing | D7: End Customer | E7: Customer Android App, Customer iOS App, Website | F7: P0 | G7: =COUNTIF('Detailed Requirements'!$A$6:$A$5000,A7) -> 5 | H7: Capture and validate service-delivery addresses and serviceability.
A8: M03 | B8: Service Catalog, Search & Discovery | C8: Customer-Facing | D8: End Customer | E8: Customer Android App, Customer iOS App, Website | F8: P0 | G8: =COUNTIF('Detailed Requirements'!$A$6:$A$5000,A8) -> 6 | H8: Browse, search and evaluate the salon & beauty service catalog.
A9: M04 | B9: Booking, Scheduling & Slot Management | C9: Customer-Facing | D9: End Customer | E9: Customer Android App, Customer iOS App, Website | F9: P0 | G9: =COUNTIF('Detailed Requirements'!$A$6:$A$5000,A9) -> 6 | H9: Core booking flow, from slot selection to confirmation.
A10: M05 | B10: Cart, Pricing, Offers & Coupons | C10: Customer-Facing | D10: End Customer | E10: Customer Android App, Customer iOS App, Website | F10: P0 | G10: =COUNTIF('Detailed Requirements'!$A$6:$A$5000,A10) -> 5 | H10: Transparent, upfront pricing — the platform's core trust differentiator.
A11: M06 | B11: Payments, Wallet & Refunds | C11: Customer-Facing | D11: End Customer | E11: Customer Android App, Customer iOS App, Website | F11: P0 | G11: =COUNTIF('Detailed Requirements'!$A$6:$A$5000,A11) -> 6 | H11: Cashless, secure payment collection and refund handling.
A12: M07 | B12: Live Order Tracking | C12: Customer-Facing | D12: End Customer | E12: Customer Android App, Customer iOS App, Website | F12: P1 | G12: =COUNTIF('Detailed Requirements'!$A$6:$A$5000,A12) -> 5 | H12: Real-time visibility into partner assignment and arrival.
A13: M08 | B13: Ratings, Reviews & Feedback | C13: Customer-Facing | D13: End Customer | E13: Customer Android App, Customer iOS App, Website | F13: P0 | G13: =COUNTIF('Detailed Requirements'!$A$6:$A$5000,A13) -> 4 | H13: Structured feedback loop closing the accountability gap.
A14: M09 | B14: Membership & Subscription Plans | C14: Customer-Facing | D14: End Customer | E14: Customer Android App, Customer iOS App, Website | F14: P1 | G14: =COUNTIF('Detailed Requirements'!$A$6:$A$5000,A14) -> 4 | H14: Recurring-revenue and retention plans.
A15: M10 | B15: Loyalty, Referral & Rewards | C15: Customer-Facing | D15: End Customer | E15: Customer Android App, Customer iOS App, Website | F15: P1 | G15: =COUNTIF('Detailed Requirements'!$A$6:$A$5000,A15) -> 4 | H15: Growth-loop mechanics for acquisition and retention.
A16: M11 | B16: Customer Support, Complaints & SOS | C16: Customer-Facing | D16: End Customer | E16: Customer Android App, Customer iOS App, Website | F16: P0 | G16: =COUNTIF('Detailed Requirements'!$A$6:$A$5000,A16) -> 5 | H16: Support and safety channel for customers.
A17: M12 | B17: Reschedule, Cancellation & Service Guarantee | C17: Customer-Facing | D17: End Customer | E17: Customer Android App, Customer iOS App, Website | F17: P0 | G17: =COUNTIF('Detailed Requirements'!$A$6:$A$5000,A17) -> 4 | H17: Booking-change and quality-remediation workflows.
... A38: M33 | B38: Security, Data Privacy & Compliance | C38: Cross-Platform & Technical | D38: All Personas | E38: All Platforms (Shared Backend) | F38: P0 | G38: =COUNTIF('Detailed Requirements'!$A$6:$A$5000,A38) -> 5 | H38: Non-negotiable platform-wide controls; treated as a first-class module, not an afterthought.
A39: TOTAL | B39: 33 Modules | G39: =SUM(G6:G38) -> 156
A42: Priority Legend | D42: Modules by Category
A43: P0 | B43: Must-Have — required for MVP / Phase 1 launch | D43: Customer-Facing | E43: 12
A44: P1 | B44: Should-Have — targeted within Phase 1, can trail MVP by a sprint or two | D44: Partner-Facing | E44: 7
A45: P2 | B45: Nice-to-Have — candidate for a later release | D45: Inventory & Supply Chain | E45: 1
D46: Admin & Back-Office | E46: 10
D47: Cross-Platform & Technical | E47: 3

Sheet Detailed Requirements
A1: BLOOM — At-Home Salon & Beauty Services Platform
A2: Detailed, Module-Wise Requirements — Full End-to-End Lifecycle
A3: Covers: Pre-Booking -> Booking & Payment -> Fulfilment -> Post-Service -> Partner Lifecycle -> Backend Ops -> Reporting
A5: Module ID | B5: Module Name | C5: Sub-Feature / Requirement | D5: Requirement Description | E5: Persona(s) | F5: Platform(s) | G5: Lifecycle Stage | H5: Priority | I5: Notes / Dependencies
A6: M01 | B6: Customer Onboarding & Profile Management | C6: OTP / SSO Login | D6: Sign-up and login via mobile OTP, email, and Google/Apple/Facebook SSO. | E6: End Customer | F6: Customer Android App, Customer iOS App, Website | G6: Pre-Booking | H6: P0 | I6: Session tokens must expire and refresh securely.
A7: M01 | B7: Customer Onboarding & Profile Management | C7: Profile Setup | D7: Capture name, gender, date of birth, profile photo. | E7: End Customer | F7: Customer Android App, Customer iOS App, Website | G7: Pre-Booking | H7: P0
A8: M01 | B8: Customer Onboarding & Profile Management | C8: Multiple Saved Addresses | D8: Link one or more saved addresses to a single profile. | E8: End Customer | F8: Customer Android App, Customer iOS App, Website | G8: Pre-Booking | H8: P0 | I8: Depends on M02 Address Management.
A9: M01 | B9: Customer Onboarding & Profile Management | C9: Preference Capture | D9: Store language and partner-gender preference where relevant to a service. | E9: End Customer | F9: Customer Android App, Customer iOS App, Website | G9: Pre-Booking | H9: P1
A10: M01 | B10: Customer Onboarding & Profile Management | C10: Guest Checkout | D10: Allow limited booking flow without full registration; convert to full profile post-booking. | E10: End Customer | F10: Customer Android App, Customer iOS App, Website | G10: Pre-Booking | H10: P2 | I10: Optional for launch.
A11: M01 | B11: Customer Onboarding & Profile Management | C11: Account Deletion & Data Export | D11: Self-serve account deletion and personal-data export for compliance. | E11: End Customer | F11: Customer Android App, Customer iOS App, Website | G11: Ongoing | H11: P1 | I11: Required for DPDP Act compliance — see M33.
A12: M02 | B12: Address & Location Management | C12: Saved Addresses | D12: Add, edit and delete multiple addresses tagged Home/Work/Other. | E12: End Customer | F12: Customer Android App, Customer iOS App, Website | G12: Pre-Booking | H12: P0
A13: M02 | B13: Address & Location Management | C13: GPS Auto-Detect | D13: Auto-detect current location on app open for faster booking. | E13: End Customer | F13: Customer Android App, Customer iOS App, Website | G13: Pre-Booking | H13: P0 | I13: Requires device location permission.
A14: M02 | B14: Address & Location Management | C14: Map Pin & Address Search | D14: Google Places-style autocomplete plus manual map-pin drop. | E14: End Customer | F14: Customer Android App, Customer iOS App, Website | G14: Pre-Booking | H14: P0 | I14: Integration: Maps API — see M32.
A15: M02 | B15: Address & Location Management | C15: Serviceability Check | D15: Validate pincode/zone against live-city coverage before showing catalog. | E15: End Customer | F15: Customer Android App, Customer iOS App, Website | G15: Pre-Booking | H15: P0 | I15: Depends on M24 Zone Configuration.
A16: M02 | B16: Address & Location Management | C16: Default Address | D16: Set and reuse a default address for repeat bookings. | E16: End Customer | F16: Customer Android App, Customer iOS App, Website | G16: Pre-Booking | H16: P1
A17: M03 | B17: Service Catalog, Search & Discovery | C17: Category Browsing | D17: Browse by category: Hair, Skin & Face, Hair Removal, Nails, Makeup, Men's Grooming, Body Care, Packages. | E17: End Customer | F17: Customer Android App, Customer iOS App, Website | G17: Pre-Booking | H17: P0
A18: M03 | B18: Service Catalog, Search & Discovery | C18: Keyword Search | D18: Search with auto-suggest across service names and categories. | E18: End Customer | F18: Customer Android App, Customer iOS App, Website | G18: Pre-Booking | H18: P0
A19: M03 | B19: Service Catalog, Search & Discovery | C19: Filter & Sort | D19: Filter/sort results by price, rating, duration and popularity. | E19: End Customer | F19: Customer Android App, Customer iOS App, Website | G19: Pre-Booking | H19: P1
A20: M03 | B20: Service Catalog, Search & Discovery | C20: Service Detail Page | D20: Description, duration, price, add-ons, before/after images and reviews per service. | E20: End Customer | F20: Customer Android App, Customer iOS App, Website | G20: Pre-Booking | H20: P0
A21: M03 | B21: Service Catalog, Search & Discovery | C21: Package / Bundle Builder | D21: Configure bundled packages (e.g., bridal, party-ready) from individual services. | E21: End Customer | F21: Customer Android App, Customer iOS App, Website | G21: Pre-Booking | H21: P1
A22: M03 | B22: Service Catalog, Search & Discovery | C22: City/Zone Catalog Variants | D22: Show only the services, pricing and availability applicable to the customer's zone. | E22: End Customer | F22: Customer Android App, Customer iOS App, Website | G22: Pre-Booking | H22: P0 | I22: Depends on M22 Service Catalog Master.
A23: M04 | B23: Booking, Scheduling & Slot Management | C23: Real-Time Slot Availability | D23: Show live available slots by zone, date and time based on partner capacity. | E23: End Customer | F23: Customer Android App, Customer iOS App, Website | G23: Booking & Payment | H23: P0 | I23: Depends on M24 Dispatch Configuration.
A24: M04 | B24: Booking, Scheduling & Slot Management | C24: Multi-Service Booking | D24: Book multiple services/add-ons in a single visit/booking. | E24: End Customer | F24: Customer Android App, Customer iOS App, Website | G24: Booking & Payment | H24: P0
A25: M04 | B25: Booking, Scheduling & Slot Management | C25: Instant vs Scheduled Booking | D25: Support both immediate on-demand booking and future-dated scheduling. | E25: End Customer | F25: Customer Android App, Customer iOS App, Website | G25: Booking & Payment | H25: P0
A26: M04 | B26: Booking, Scheduling & Slot Management | C26: Preferred-Partner Selection | D26: Allow repeat customers to request the same partner where available. | E26: End Customer | F26: Customer Android App, Customer iOS App, Website | G26: Booking & Payment | H26: P1
A27: M04 | B27: Booking, Scheduling & Slot Management | C27: Booking Confirmation & ETA | D27: Confirm booking with partner-assignment status and estimated arrival window. | E27: End Customer | F27: Customer Android App, Customer iOS App, Website | G27: Booking & Payment | H27: P0
A28: M04 | B28: Booking, Scheduling & Slot Management | C28: Calendar/Reminder Sync | D28: Add booking to device calendar with reminder. | E28: End Customer | F28: Customer Android App, Customer iOS App, Website | G28: Booking & Payment | H28: P2
A29: M05 | B29: Cart, Pricing, Offers & Coupons | C29: Dynamic Cart | D29: Line-item cart reflecting selected services, add-ons and quantities. | E29: End Customer | F29: Customer Android App, Customer iOS App, Website | G29: Booking & Payment | H29: P0
A30: M05 | B30: Cart, Pricing, Offers & Coupons | C30: Coupon Application | D30: Apply and validate coupon codes with eligibility and usage-limit checks. | E30: End Customer | F30: Customer Android App, Customer iOS App, Website | G30: Booking & Payment | H30: P0 | I30: Depends on M23 Offer Configuration.
A31: M05 | B31: Cart, Pricing, Offers & Coupons | C31: Auto-Applied Discounts | D31: First-booking and referral discounts applied automatically where eligible. | E31: End Customer | F31: Customer Android App, Customer iOS App, Website | G31: Booking & Payment | H31: P1
A32: M05 | B32: Cart, Pricing, Offers & Coupons | C32: Tax (GST) Computation | D32: Compute and display applicable GST on the final price. | E32: End Customer | F32: Customer Android App, Customer iOS App, Website | G32: Booking & Payment | H32: P0
A33: M05 | B33: Cart, Pricing, Offers & Coupons | C33: Price Breakup Transparency | D33: Itemized breakup screen shown before payment — no on-site renegotiation. | E33: End Customer | F33: Customer Android App, Customer iOS App, Website | G33: Booking & Payment | H33: P0 | I33: Core trust requirement per business model.
A34: M06 | B34: Payments, Wallet & Refunds | C34: Multiple Payment Modes | D34: UPI, cards, net-banking and wallets at minimum; COD optional/limited. | E34: End Customer | F34: Customer Android App, Customer iOS App, Website | G34: Booking & Payment | H34: P0 | I34: Integration: Payment Gateway — see M32.
A35: M06 | B35: Payments, Wallet & Refunds | C35: In-App Wallet | D35: Store credits, cashback and refund balances for future use. | E35: End Customer | F35: Customer Android App, Customer iOS App, Website | G35: Booking & Payment | H35: P1
A36: M06 | B36: Payments, Wallet & Refunds | C36: Payment Retry & Failure Handling | D36: Graceful retry flow and clear messaging on payment failure. | E36: End Customer | F36: Customer Android App, Customer iOS App, Website | G36: Booking & Payment | H36: P0
A37: M06 | B37: Payments, Wallet & Refunds | C37: Auto-Refund Workflow | D37: Trigger refund-to-source or wallet-credit automatically on eligible cancellations. | E37: End Customer | F37: Customer Android App, Customer iOS App, Website | G37: Post-Service | H37: P0 | I37: Depends on M12 Cancellation & Guarantee.
A38: M06 | B38: Payments, Wallet & Refunds | C38: GST-Compliant Invoicing | D38: Generate downloadable invoice/receipt per booking. | E38: End Customer | F38: Customer Android App, Customer iOS App, Website | G38: Post-Service | H38: P0
A39: M06 | B39: Payments, Wallet & Refunds | C39: Saved/Tokenized Payment Methods | D39: Securely save cards/UPI handles for repeat use (tokenized, PCI-DSS compliant). | E39: End Customer | F39: Customer Android App, Customer iOS App, Website | G39: Booking & Payment | H39: P1 | I39: See M33 Security & Compliance.
A40: M07 | B40: Live Order Tracking | C40: Live Partner Location | D40: Show partner's real-time location on map from dispatch to arrival. | E40: End Customer | F40: Customer Android App, Customer iOS App, Website | G40: Fulfilment | H40: P0 | I40: Integration: Maps/GPS — see M32.
A41: M07 | B41: Live Order Tracking | C41: Booking Status Timeline | D41: Visual status: Confirmed → Partner Assigned → En Route → Arrived → In Service → Completed. | E41: End Customer | F41: Customer Android App, Customer iOS App, Website | G41: Fulfilment | H41: P0
A42: M07 | B42: Live Order Tracking | C42: ETA & Delay Alerts | D42: Display ETA and proactively notify on delays. | E42: End Customer | F42: Customer Android App, Customer iOS App, Website | G42: Fulfilment | H42: P1
A43: M07 | B43: Live Order Tracking | C43: Partner Profile Card | D43: Show partner photo, rating and verification badge before arrival. | E43: End Customer | F43: Customer Android App, Customer iOS App, Website | G43: Fulfilment | H43: P0
A44: M07 | B44: Live Order Tracking | C44: Masked Call/Chat | D44: In-app masked-number call or chat with the assigned partner. | E44: End Customer | F44: Customer Android App, Customer iOS App, Website | G44: Fulfilment | H44: P1
A45: M08 | B45: Ratings, Reviews & Feedback | C45: Mandatory Post-Service Rating | D45: Prompt a star rating (and optional text review) after every completed booking. | E45: End Customer | F45: Customer Android App, Customer iOS App, Website | G45: Post-Service | H45: P0 | I45: Feeds M18 Partner Scorecard.
A46: M08 | B46: Ratings, Reviews & Feedback | C46: Structured Feedback Tags | D46: Tag feedback by hygiene, punctuality, skill and behaviour. | E46: End Customer | F46: Customer Android App, Customer iOS App, Website | G46: Post-Service | H46: P1
A47: M08 | B47: Ratings, Reviews & Feedback | C47: Photo Upload with Review | D47: Optional before/after photo attached to a review. | E47: End Customer | F47: Customer Android App, Customer iOS App, Website | G47: Post-Service | H47: P2
A48: M08 | B48: Ratings, Reviews & Feedback | C48: Review Moderation Queue | D48: Admin queue to moderate/flag inappropriate reviews before publishing. | E48: End Customer | F48: Customer Android App, Customer iOS App, Website | G48: Post-Service | H48: P1 | I48: Admin-side; see M30.
A49: M09 | B49: Membership & Subscription Plans | C49: Plan Tiers | D49: Monthly/quarterly/annual tiers with defined benefits (priority slots, discounted pricing, bundled services). | E49: End Customer | F49: Customer Android App, Customer iOS App, Website | G49: Post-Service | H49: P1 | I49: Depends on M23 configuration.
A50: M09 | B50: Membership & Subscription Plans | C50: Purchase & Auto-Renewal | D50: Subscribe, auto-renew and cancel a plan in-app. | E50: End Customer | F50: Customer Android App, Customer iOS App, Website | G50: Post-Service | H50: P1
A51: M09 | B51: Membership & Subscription Plans | C51: Entitlement Usage Tracking | D51: Track consumption of plan-included services against entitlement. | E51: End Customer | F51: Customer Android App, Customer iOS App, Website | G51: Post-Service | H51: P1
A52: M09 | B52: Membership & Subscription Plans | C52: Plan-Aware Pricing | D52: Cart automatically reflects membership pricing/discount where applicable. | E52: End Customer | F52: Customer Android App, Customer iOS App, Website | G52: Booking & Payment | H52: P1
A53: M10 | B53: Loyalty, Referral & Rewards | C53: Referral Code & Sharing | D53: Generate a unique referral code and shareable link/message. | E53: End Customer | F53: Customer Android App, Customer iOS App, Website | G53: Post-Service | H53: P1
A54: M10 | B54: Loyalty, Referral & Rewards | C54: Referral Reward Credit | D54: Credit both referrer and referee on the referee's successful first booking. | E54: End Customer | F54: Customer Android App, Customer iOS App, Website | G54: Post-Service | H54: P1 | I54: Depends on M06 Wallet.
A55: M10 | B55: Loyalty, Referral & Rewards | C55: Loyalty Points | D55: Accrue and redeem loyalty points against bookings. | E55: End Customer | F55: Customer Android App, Customer iOS App, Website | G55: Post-Service | H55: P2
A56: M10 | B56: Loyalty, Referral & Rewards | C56: Rebooking Nudges | D56: Personalized push/SMS nudges timed to a service's typical rebooking cycle. | E56: End Customer | F56: Customer Android App, Customer iOS App, Website | G56: Post-Service | H56: P1 | I56: Depends on M31 Notification Engine.
A57: M11 | B57: Customer Support, Complaints & SOS | C57: Help Center / FAQ | D57: Self-serve FAQ and help articles in-app. | E57: End Customer | F57: Customer Android App, Customer iOS App, Website | G57: Ongoing | H57: P0
A58: M11 | B58: Customer Support, Complaints & SOS | C58: Ticket Raising | D58: Raise a support ticket categorized by billing, service quality, partner conduct or safety. | E58: End Customer | F58: Customer Android App, Customer iOS App, Website | G58: Ongoing | H58: P0
A59: M11 | B59: Customer Support, Complaints & SOS | C59: Live Chat / Chatbot | D59: First-line chatbot with escalation to a human agent. | E59: End Customer | F59: Customer Android App, Customer iOS App, Website | G59: Ongoing | H59: P1
A60: M11 | B60: Customer Support, Complaints & SOS | C60: In-App SOS | D60: Emergency SOS button sharing live location with ops/emergency contacts. | E60: End Customer | F60: Customer Android App, Customer iOS App, Website | G60: Fulfilment | H60: P0 | I60: Safety-critical; see M33.
A61: M11 | B61: Customer Support, Complaints & SOS | C61: Complaint SLA Tracking | D61: Track and surface resolution status and SLA against every open ticket. | E61: End Customer | F61: Customer Android App, Customer iOS App, Website | G61: Ongoing | H61: P0 | I61: Feeds M30 Quality Report.
A62: M12 | B62: Reschedule, Cancellation & Service Guarantee | C62: Self-Serve Reschedule | D62: Reschedule a booking within the configured policy window. | E62: End Customer | F62: Customer Android App, Customer iOS App, Website | G62: Booking & Payment | H62: P0
A63: M12 | B63: Reschedule, Cancellation & Service Guarantee | C63: Tiered Cancellation Logic | D63: Apply cancellation fee rules based on notice period. | E63: End Customer | F63: Customer Android App, Customer iOS App, Website | G63: Booking & Payment | H63: P0 | I63: Depends on M23 configuration.
A64: M12 | B64: Reschedule, Cancellation & Service Guarantee | C64: Redo / Service-Guarantee Claim | D64: Raise a claim for an unsatisfactory service; route to Admin for adjudication. | E64: End Customer | F64: Customer Android App, Customer iOS App, Website | G64: Post-Service | H64: P0
A65: M12 | B65: Reschedule, Cancellation & Service Guarantee | C65: Guarantee-Linked Refund | D65: Auto-trigger refund/credit or a free redo based on claim outcome. | E65: End Customer | F65: Customer Android App, Customer iOS App, Website | G65: Post-Service | H65: P0 | I65: Depends on M06 Refunds.
A66: M13 | B66: Partner Recruitment & Application | C66: Public Recruitment Landing Page | D66: Web landing page for prospective partners to register interest. | E66: Partner | F66: Partner App (Android & iOS) + Public Website | G66: Partner Lifecycle | H66: P0 | I66: Lives on public Website.
A67: M13 | B67: Partner Recruitment & Application | C67: In-App Application Form | D67: Capture skills, experience, service categories and location. | E67: Partner | F67: Partner App (Android & iOS) + Public Website | G67: Partner Lifecycle | H67: P0
A68: M13 | B68: Partner Recruitment & Application | C68: Application Status Tracking | D68: Show applicant their status: Submitted / Under Review / Approved / Rejected. | E68: Partner | F68: Partner App (Android & iOS) + Public Website | G68: Partner Lifecycle | H68: P1
A69: M13 | B69: Partner Recruitment & Application | C69: Partner-Refers-Partner | D69: Referral mechanism for existing partners to refer new applicants. | E69: Partner | F69: Partner App (Android & iOS) + Public Website | G69: Partner Lifecycle | H69: P2
A70: M14 | B70: Partner KYC & Background Verification | C70: Document Upload | D70: Upload ID proof, address proof, photo and skill certificates. | E70: Partner + Administrator | F70: Partner App + Admin Web Console | G70: Partner Lifecycle | H70: P0
A71: M14 | B71: Partner KYC & Background Verification | C71: Background-Verification Integration | D71: Submit and retrieve results from a third-party ID/police-verification API. | E71: Partner + Administrator | F71: Partner App + Admin Web Console | G71: Partner Lifecycle | H71: P0 | I71: Integration — see M32.
A72: M14 | B72: Partner KYC & Background Verification | C72: Verification Review Queue | D72: Admin queue to review, approve or reject verification cases. | E72: Partner + Administrator | F72: Partner App + Admin Web Console | G72: Partner Lifecycle | H72: P0 | I72: Admin-side.
A73: M14 | B73: Partner KYC & Background Verification | C73: Re-Verification Reminders | D73: Scheduled reminders for periodic re-verification/renewal. | E73: Partner + Administrator | F73: Partner App + Admin Web Console | G73: Partner Lifecycle | H73: P1
A74: M15 | B74: Partner Training & Certification | C74: Training Content Library | D74: Video/SOP modules per service category, managed centrally. | E74: Partner + Administrator | F74: Partner App + Admin Web Console | G74: Partner Lifecycle | H74: P0 | I74: Content authored via M28 CMS.
A75: M15 | B75: Partner Training & Certification | C75: Certification Test & Scoring | D75: In-app assessment with pass/fail scoring gating go-live. | E75: Partner + Administrator | F75: Partner App + Admin Web Console | G75: Partner Lifecycle | H75: P0
A76: M15 | B76: Partner Training & Certification | C76: Hygiene-Protocol Certification | D76: Mandatory sealed single-use-kit protocol certification before first booking. | E76: Partner + Administrator | F76: Partner App + Admin Web Console | G76: Partner Lifecycle | H76: P0 | I76: Core trust requirement.
A77: M15 | B77: Partner Training & Certification | C77: Refresher/Recertification | D77: Periodic recertification scheduling and tracking. | E77: Partner + Administrator | F77: Partner App + Admin Web Console | G77: Partner Lifecycle | H77: P1
A78: M15 | B78: Partner Training & Certification | C78: Training-Fee Payment | D78: Collect a paid-onboarding/upskilling fee where the business model requires it. | E78: Partner + Administrator | F78: Partner App + Admin Web Console | G78: Partner Lifecycle | H78: P2 | I78: Depends on M17/M29 for payment rails.
A79: M16 | B79: Partner Job Dispatch & On-Ground Execution | C79: Job Push & Accept/Reject | D79: Push new bookings to the nearest qualified, available partner with an accept/reject window. | E79: Partner | F79: Partner App (Android & iOS) | G79: Fulfilment | H79: P0 | I79: Depends on M24 Dispatch Configuration.
A80: M16 | B80: Partner Job Dispatch & On-Ground Execution | C80: Zone-Based Auto-Assignment | D80: Algorithm matching bookings to partners by zone, travel time and skill fit. | E80: Partner | F80: Partner App (Android & iOS) | G80: Fulfilment | H80: P0
A81: M16 | B81: Partner Job Dispatch & On-Ground Execution | C81: Navigation Integration | D81: Turn-by-turn navigation to the customer address. | E81: Partner | F81: Partner App (Android & iOS) | G81: Fulfilment | H81: P0 | I81: Integration: Maps API.
A82: M16 | B82: Partner Job Dispatch & On-Ground Execution | C82: Digital Service Checklist | D82: Step-by-step in-app checklist including visible kit-unsealing confirmation and before/after photo. | E82: Partner | F82: Partner App (Android & iOS) | G82: Fulfilment | H82: P0 | I82: Core hygiene/trust requirement.
A83: M16 | B83: Partner Job Dispatch & On-Ground Execution | C83: Job Status Updates | D83: Partner updates status: En Route / Arrived / Started / Completed. | E83: Partner | F83: Partner App (Android & iOS) | G83: Fulfilment | H83: P0 | I83: Drives M07 Live Tracking for customer.
A84: M16 | B84: Partner Job Dispatch & On-Ground Execution | C84: Daily Job Queue View | D84: See and sequence all jobs scheduled for the day. | E84: Partner | F84: Partner App (Android & iOS) | G84: Fulfilment | H84: P1
A85: M17 | B85: Partner Earnings, Payouts & Incentives | C85: Real-Time Earnings Dashboard | D85: Per-job, daily and weekly earnings visible in the partner app. | E85: Partner + Administrator | F85: Partner App + Admin Web Console | G85: Partner Lifecycle | H85: P0
A86: M17 | B86: Partner Earnings, Payouts & Incentives | C86: Commission-Tier Logic | D86: Reduced commission for top-performing/high-retention partners. | E86: Partner + Administrator | F86: Partner App + Admin Web Console | G86: Partner Lifecycle | H86: P0 | I86: Depends on M23 configuration.
A87: M17 | B87: Partner Earnings, Payouts & Incentives | C87: Payout Cycle & Bank/UPI Integration | D87: Configurable payout cycle (daily/weekly) with bank/UPI disbursal. | E87: Partner + Administrator | F87: Partner App + Admin Web Console | G87: Partner Lifecycle | H87: P0 | I87: Integration — see M32.
A88: M17 | B88: Partner Earnings, Payouts & Incentives | C88: Incentive/Bonus Rule Engine | D88: Volume, rating and referral-based bonus calculation. | E88: Partner + Administrator | F88: Partner App + Admin Web Console | G88: Partner Lifecycle | H88: P1
A89: M17 | B89: Partner Earnings, Payouts & Incentives | C89: Payout Statements & Tax Docs | D89: Downloadable payout history and TDS documentation. | E89: Partner + Administrator | F89: Partner App + Admin Web Console | G89: Partner Lifecycle | H89: P0 | I89: Depends on M29 Financial Reconciliation.
A90: M18 | B90: Partner Performance, Ratings & Quality Audit | C90: Partner Scorecard | D90: Aggregate rating, completion rate, punctuality and hygiene-compliance score. | E90: Partner + Administrator | F90: Partner App + Admin Web Console | G90: Partner Lifecycle | H90: P0 | I90: Fed by M08 Ratings.
A91: M18 | B91: Partner Performance, Ratings & Quality Audit | C91: Mystery-Shopper Audit | D91: Admin-scheduled covert audits with structured scoring. | E91: Partner + Administrator | F91: Partner App + Admin Web Console | G91: Partner Lifecycle | H91: P1 | I91: Admin-side.
A92: M18 | B92: Partner Performance, Ratings & Quality Audit | C92: Strike & De-Boarding Workflow | D92: Log violations, apply strikes and trigger de-boarding at threshold. | E92: Partner + Administrator | F92: Partner App + Admin Web Console | G92: Partner Lifecycle | H92: P0
A93: M18 | B93: Partner Performance, Ratings & Quality Audit | C93: Recognition/Leaderboard | D93: Optional gamified recognition for top partners. | E93: Partner + Administrator | F93: Partner App + Admin Web Console | G93: Partner Lifecycle | H93: P2
A94: M19 | B94: Partner Support & SOS | C94: Partner Help Center & Ticketing | D94: Self-serve help and ticket-raising for partners. | E94: Partner | F94: Partner App (Android & iOS) | G94: Ongoing | H94: P1
A95: M19 | B95: Partner Support & SOS | C95: In-App SOS for Partners | D95: Emergency alert from the partner side while inside a customer's home. | E95: Partner | F95: Partner App (Android & iOS) | G95: Fulfilment | H95: P0 | I95: Safety-critical; see M33.
A96: M19 | B96: Partner Support & SOS | C96: Dispute Resolution | D96: Structured workflow for payment disputes and customer-conduct complaints. | E96: Partner | F96: Partner App (Android & iOS) | G96: Ongoing | H96: P1
A97: M20 | B97: Consumable Kit & Inventory Management (SKU / Warehouse) | C97: SKU Master | D97: Master list of consumable-kit SKUs and private-label retail-product SKUs, with unit cost and category. | E97: Partner + Administrator | F97: Partner App + Admin Web Console | G97: Backend Ops | H97: P0 | I97: Feeds M30 Inventory/SKU Report.
A98: M20 | B98: Consumable Kit & Inventory Management (SKU / Warehouse) | C98: Central Warehouse Stock Tracking | D98: Track stock-on-hand per SKU per warehouse/zone with reorder-point alerts. | E98: Partner + Administrator | F98: Partner App + Admin Web Console | G98: Backend Ops | H98: P0
A99: M20 | B99: Consumable Kit & Inventory Management (SKU / Warehouse) | C99: Kit Request Workflow | D99: Partner requests kit replenishment in-app; ops fulfils and dispatches. | E99: Partner + Administrator | F99: Partner App + Admin Web Console | G99: Fulfilment | H99: P0
A100: M20 | B100: Consumable Kit & Inventory Management (SKU / Warehouse) | C100: Per-Booking Kit Consumption Log | D100: Log the specific SKU(s) consumed against each booking ID for true per-booking cost. | E100: Partner + Administrator | F100: Partner App + Admin Web Console | G100: Fulfilment | H100: P0 | I100: Core input to profitability reporting.
A101: M20 | B101: Consumable Kit & Inventory Management (SKU / Warehouse) | C101: Private-Label Product Catalog | D101: Catalog of proprietary skincare/haircare products sold direct-to-consumer during bookings. | E101: Partner + Administrator | F101: Partner App + Admin Web Console | G101: Backend Ops | H101: P1 | I101: Revenue stream per business model.
...
